nic_api/__init__.py
nic_api/exceptions.py
nic_api/models.py
nic_api-1.1.0.dist-info/METADATA
nic_api-1.1.0.dist-info/WHEEL
nic_api-1.1.0.dist-info/licenses/LICENSE
nic_api-1.1.0.dist-info/RECORD
